[
    {
        "id": "b0",
        "img": "img/bigphoto/portfolio-ph-01.jpg"
    },
    {
        "id": "b1",
        "img": "img/bigphoto/portfolio-ph-02.jpg"
    },
    {
        "id": "b2",
        "img": "img/bigphoto/portfolio-ph-03.jpg"
    },
    {
        "id": "b3",
        "img": "img/bigphoto/portfolio-ph-04.jpg"
    },
    {
        "id": "b4",
        "img": "img/bigphoto/portfolio-ph-05.jpg"
    },
    {
        "id": "b5",
        "img": "img/bigphoto/portfolio-ph-06.jpg"
    },
    {
        "id": "b6",
        "img": "img/bigphoto/portfolio-ph-07.jpg"
    },
    {
        "id": "b7",
        "img": "img/bigphoto/portfolio-ph-08.jpg"
    },
    {
        "id": "b8",
        "img": "img/bigphoto/portfolio-ph-09.jpg"
    },
    {
        "id": "b9",
        "img": "img/bigphoto/portfolio-ph-10.jpg"
    },
    {
        "id": "b10",
        "img": "img/bigphoto/portfolio-ph-11.jpg"
    },
    {
        "id": "b11",
        "img": "img/bigphoto/portfolio-ph-12.jpg"
    }
]